pinv-run.py
setup.py
pinv/__init__.py
pinv/mod1.py
pinv/mod2.py
pinv.egg-info/PKG-INFO
pinv.egg-info/SOURCES.txt
pinv.egg-info/dependency_links.txt
pinv.egg-info/top_level.txt