Metadata-Version: 1.1
Name: pinv
Version: 0.0.1a
Summary: pinv is pluggable inventory service
Home-page: https://bitbucket.org/btoic/python-pinv/get/master.tar.gz
Author: Branko Toic
Author-email: branko@toic.org
License: GPLv2
Platform: unix
Provides: pinv
